arc/__init__.py
arc/autolinker/__init__.py
arc/autolinker/autolinker.py
arc/autolinker/cleaning_utils.py
arc/autolinker/splink_mlflow.py
arc/lib/__init__.py
arc/lib/arc-0.1.18-jar-with-dependencies.jar
arc/lib/arc-0.1.18.jar
arc/sql/__init__.py
arc/sql/enable_arc.py
arc/sql/functions/__init__.py
arc/sql/functions/functions.py
arc/sql/functions/library_handler.py
arc/utils/__init__.py
arc/utils/utils.py
test/__init__.py
test/test_arc_sql.py
test/test_cleaning.py
test/utils/__init__.py
test/utils/arc_test.py
test/utils/spark_test_case.py
databricks_arc-0.1.18.dist-info/METADATA
databricks_arc-0.1.18.dist-info/WHEEL
databricks_arc-0.1.18.dist-info/top_level.txt
databricks_arc-0.1.18.dist-info/RECORD
