Metadata-Version: 2.1
Name: databricks-arc
Version: 0.1.18
Summary: ARC: data linking solution for Databricks with Splink
Home-page: https://github.com/databricks-industry-solutions/splink-public-sector-hackathon
Author: Databricks
License: Databricks License
Classifier: License :: Other/Proprietary License
Classifier: Topic :: Scientific/Engineering :: Information Analysis
Classifier: Programming Language :: Python
Classifier: Programming Language :: Python :: 3
Classifier: Programming Language :: Python :: 3.7
Requires-Python: >=3.7.0
Requires-Dist: ipython ==7.22.0
Requires-Dist: splink ==3.9.4
Provides-Extra: dev
Requires-Dist: isort ; extra == 'dev'
Requires-Dist: black ; extra == 'dev'
Requires-Dist: build ; extra == 'dev'
